MANIFEST.in
README
setup.py
aspic/__init__.py
aspic/const.py
aspic/header.py
aspic/manager.py
aspic/message.py
aspic/qmotor.py
aspic/qommand.py
aspic/qonnection.py
aspic/qounter.py
aspic/reply.py
aspic.egg-info/PKG-INFO
aspic.egg-info/SOURCES.txt
aspic.egg-info/dependency_links.txt
aspic.egg-info/top_level.txt