Metadata-Version: 1.0
Name: aspic
Version: 2018.10.10
Summary: Qt version of SpecClient for Python 3.6+
Home-page: https://hg.3lp.cx/aspic
Author: Vadim Dyadkin
Author-email: dyadkin@gmail.com
License: GPLv3
Platform: UNKNOWN
